fastai_datasets/__init__.py
fastai_datasets/_modidx.py
fastai_datasets/all.py
fastai_datasets/cifar.py
fastai_datasets/imagenette.py
fastai_datasets/lfw.py
fastai_datasets/mnist.py
fastai_datasets/pairs.py
fastai_datasets/patches.py
fastai_datasets/pfr.py
fastai_datasets/utils.py
fastai_datasets-0.0.8.dist-info/LICENSE
fastai_datasets-0.0.8.dist-info/METADATA
fastai_datasets-0.0.8.dist-info/WHEEL
fastai_datasets-0.0.8.dist-info/entry_points.txt
fastai_datasets-0.0.8.dist-info/top_level.txt
fastai_datasets-0.0.8.dist-info/RECORD
