Metadata-Version: 2.1
Name: fastai-datasets
Version: 0.0.8
Summary: Leveraging fastai to easily load and handle datasets
Home-page: https://github.com/Irad-Zehavi/fastai-datasets
Author: iradz
Author-email: irad.zehavi@outlook.com
License: Apache Software License 2.0
Keywords: nbdev jupyter notebook python
Platform: UNKNOWN
Classifier: Development Status :: 4 - Beta
Classifier: Intended Audience :: Developers
Classifier: Natural Language :: English
Classifier: Programming Language :: Python :: 3.7
Classifier: Programming Language :: Python :: 3.8
Classifier: Programming Language :: Python :: 3.9
Classifier: Programming Language :: Python :: 3.10
Classifier: License :: OSI Approved :: Apache Software License
Requires-Python: >=3.7
Requires-Dist: facenet-pytorch
Requires-Dist: fastai
Provides-Extra: dev
Requires-Dist: nbdev ; extra == 'dev'
